voiceChain/__init__.py
voiceChain/audio/__init.py
voiceChain/audio/player.py
voiceChain/audio/recorder.py
voiceChain/audio/vad.py
voiceChain/core/__init__.py
voiceChain/core/llm.py
voiceChain/core/stt.py
voiceChain/core/tts.py
voiceChain/pipeline/__init__.py
voiceChain/pipeline/manager.py
voiceChain/pipeline/runner.py
voiceChain/pipeline/services.py
voiceChain/utils/__init__.py
voiceChain/utils/logging.py
voiceChain/utils/state.py
voicechain-0.1.1.dist-info/METADATA
voicechain-0.1.1.dist-info/WHEEL
voicechain-0.1.1.dist-info/top_level.txt
voicechain-0.1.1.dist-info/RECORD
