Metadata-Version: 2.4
Name: voiceChain
Version: 0.1.1
Summary: A modular, voice conversation pipeline using MLX.
Author-email: Fady Mohamed <contact@fadymohamed.com>
Project-URL: Homepage, https://github.com/fady17/voiceChain.git
Classifier: Programming Language :: Python :: 3
Classifier: License :: OSI Approved :: MIT License
Classifier: Operating System :: MacOS
Classifier: Topic :: Scientific/Engineering :: Artificial Intelligence
Requires-Python: >=3.9
Requires-Dist: numpy
Requires-Dist: scipy
Requires-Dist: llama-cpp-python
Requires-Dist: mlx-whisper
Requires-Dist: loguru
Requires-Dist: pyaudio
Requires-Dist: webrtcvad-wheels
Requires-Dist: torch
Requires-Dist: soundfile
Requires-Dist: mlx-audio
Requires-Dist: sounddevice
Requires-Dist: mlx
